{
  "file_name": "10Marla_GF_FP_026_V01.png",
  "plot_type": "10Marla",
  "floor_level": "GF",
  "plan_type": "FP",
  "fp_number": "026",
  "version": "V01",
  "dimensions": {
    "feet": [
      35,
      65
    ],
    "inches": [
      8.833,
      16.344
    ],
    "pixels": [
      849,
      1570
    ],
    "dpi": 96,
    "aspect_ratio": 0.541,
    "bit_depth": 24
  },
  "room_counts": {
    "Bedroom": 1,
    "Bathroom": 1,
    "Kitchen": 1,
    "DrawingRoom": 1,
    "Garage": 1,
    "Lounge": 1,
    "Stairs": 38,
    "OpenSpace": 1,
    "PrayerRoom": 1,
    "Passage": 1
  },
  "room_areas_pixels": {
    "Bedroom": 156558,
    "Bathroom": 45360,
    "Kitchen": 129046,
    "DrawingRoom": 194462,
    "Garage": 330756,
    "Lounge": 234754,
    "Stairs": 42068,
    "OpenSpace": 24276,
    "PrayerRoom": 425,
    "Passage": 68803
  },
  "total_area_pixels": 1226508,
  "room_areas_sqft": {
    "Bedroom": 267.21,
    "Bathroom": 77.42,
    "Kitchen": 220.25,
    "DrawingRoom": 331.9,
    "Garage": 564.52,
    "Lounge": 400.67,
    "Stairs": 71.8,
    "OpenSpace": 41.43,
    "PrayerRoom": 0.73,
    "Passage": 117.43
  },
  "room_instances_sqft": {
    "Bedroom": [
      267.21
    ],
    "Bathroom": [
      77.42
    ],
    "Kitchen": [
      220.25
    ],
    "DrawingRoom": [
      331.9
    ],
    "Garage": [
      564.52
    ],
    "Lounge": [
      400.67
    ],
    "Stairs": [
      7.08,
      3.03,
      3.02,
      2.32,
      2.32,
      2.32,
      2.32,
      2.32,
      2.21,
      2.21,
      2.21,
      2.21,
      2.21,
      2.21,
      2.18,
      2.08,
      2.08,
      2.08,
      2.07,
      2.06,
      1.98,
      1.98,
      1.44,
      1.35,
      1.17,
      1.16,
      1.07,
      1.07,
      1.07,
      1.07,
      1.02,
      1.0,
      1.0,
      1.0,
      1.0,
      0.99,
      0.97,
      0.94
    ],
    "OpenSpace": [
      41.43
    ],
    "PrayerRoom": [
      0.73
    ],
    "Passage": [
      117.43
    ]
  },
  "analysis_date": "2025-04-29 00:26:39"
}