{
  "file_name": "10Marla_GF_FP_031_V02.png",
  "parsed_plot_type": "10Marla",
  "floor_level": "GF",
  "plan_type": "FP",
  "fp_number": "031",
  "version": "V02",
  "image_actual_width_px": 512,
  "image_actual_height_px": 927,
  "image_configured_standardized_width_px": 512,
  "image_configured_standardized_height_px": 927,
  "plot_physical_area_sqft": 2275,
  "calculated_area_per_pixel_sqft": 0.00479327,
  "room_counts": {
    "Bedroom": 1,
    "Bathroom": 3,
    "Kitchen": 1,
    "DrawingRoom": 1,
    "Garage": 1,
    "Lounge": 1,
    "Stairs": 20,
    "Lobby": 1,
    "Lawn": 1,
    "ServantQuarter": 1,
    "Passage": 1,
    "DressingArea": 1
  },
  "room_total_areas_pixels": {
    "Bedroom": 37363,
    "Bathroom": 19446,
    "Kitchen": 13817,
    "DrawingRoom": 30192,
    "Garage": 72087,
    "Lounge": 67486,
    "Stairs": 4816,
    "Lobby": 8036,
    "Lawn": 44832,
    "ServantQuarter": 8420,
    "Passage": 74230,
    "DressingArea": 4183
  },
  "overall_total_counted_pixels": 384908,
  "room_instance_areas_pixels": {
    "Bedroom": [
      37363
    ],
    "Bathroom": [
      9046,
      6690,
      3710
    ],
    "Kitchen": [
      13817
    ],
    "DrawingRoom": [
      30192
    ],
    "Garage": [
      72087
    ],
    "Lounge": [
      67486
    ],
    "Stairs": [
      501,
      473,
      330,
      329,
      320,
      320,
      316,
      309,
      215,
      192,
      177,
      174,
      150,
      150,
      150,
      150,
      140,
      140,
      140,
      140
    ],
    "Lobby": [
      8036
    ],
    "Lawn": [
      44832
    ],
    "ServantQuarter": [
      8420
    ],
    "Passage": [
      74230
    ],
    "DressingArea": [
      4183
    ]
  },
  "room_total_areas_sqft": {
    "Bedroom": 179.09,
    "Bathroom": 93.21,
    "Kitchen": 66.23,
    "DrawingRoom": 144.72,
    "Garage": 345.53,
    "Lounge": 323.48,
    "Stairs": 23.08,
    "Lobby": 38.52,
    "Lawn": 214.89,
    "ServantQuarter": 40.36,
    "Passage": 355.8,
    "DressingArea": 20.05
  },
  "overall_total_counted_sqft": 1844.97,
  "room_instance_areas_sqft": {
    "Bedroom": [
      179.09
    ],
    "Bathroom": [
      43.36,
      32.07,
      17.78
    ],
    "Kitchen": [
      66.23
    ],
    "DrawingRoom": [
      144.72
    ],
    "Garage": [
      345.53
    ],
    "Lounge": [
      323.48
    ],
    "Stairs": [
      2.4,
      2.27,
      1.58,
      1.58,
      1.53,
      1.53,
      1.51,
      1.48,
      1.03,
      0.92,
      0.85,
      0.83,
      0.72,
      0.72,
      0.72,
      0.72,
      0.67,
      0.67,
      0.67,
      0.67
    ],
    "Lobby": [
      38.52
    ],
    "Lawn": [
      214.89
    ],
    "ServantQuarter": [
      40.36
    ],
    "Passage": [
      355.8
    ],
    "DressingArea": [
      20.05
    ]
  },
  "physical_plot_info_ref": {
    "physical_dims_ft": [
      35,
      65
    ],
    "physical_area_sqft": 2275
  },
  "analysis_date": "2025-05-12 02:25:13"
}